Workbook

Sheet IncomeStatement check
A1: Exhibit 1: Income Statements (FY 2023–2025) (All figures in USD thousands) | E1: Validation Missing Value | H1: Share on Total Revenue | K1: Variations | M1: Variation Analysis
A2: Column1 | B2: FY 2023 | C2: FY 2024 | D2: FY 2025 | E2: FY 20232 | F2: FY 20242 | G2: FY 20253 | H2: FY 20232 | I2: FY 20242 | J2: FY 20253 | K2: FY 2024/2023 | L2: FY 2025/2024 | M2: Severety 2024 vs 2023 | N2: Severety 2025 vs 2024 | O2: Size
A3: P&C Commission Income | B3: 5840 | C3: 6420 | D3: 7180 | E3: =+'IncomeStatement check'!$B3/$B$8 -> 0.83488206 | F3: =+'IncomeStatement check'!$C3/$C$8 -> 0.82149712 | G3: =+'IncomeStatement check'!$D3/$D$8 -> 0.74674987 | H3: =+B3/$B$8 -> 0.83488206 | I3: =+C3/$C$8 -> 0.82149712 | J3: =+D3/$D$8 -> 0.74674987 | K3: =(C3-B3)/ABS(B3) -> 0.099315068 | L3: =(D3-C3)/ABS(C3) -> 0.11838006 | M3: =+IF(ABS(K3)<10%,"Low",IF(ABS(K3)<20%,"Medium",IF(ABS(K3)<30%,"High","Extraordinary"))) -> Low | N3: =+IF(ABS(L3)<10%,"Low",IF(ABS(L3)<20%,"Medium",IF(ABS(L3)<30%,"High","Extraordinary"))) -> Medium | O3: =IF(MAX(H3:J3)>=10%,"Large",IF(MAX(H3:J3)>=5%,"Medium","Small")) -> Large
A4: Contingent Commissions | B4: 680 | C4: 740 | D4: 1240 | E4: =+'IncomeStatement check'!$B4/$B$8 -> 0.097212294 | F4: =+'IncomeStatement check'!$C4/$C$8 -> 0.094689699 | G4: =+'IncomeStatement check'!$D4/$D$8 -> 0.12896516 | H4: =+B4/$B$8 -> 0.097212294 | I4: =+C4/$C$8 -> 0.094689699 | J4: =+D4/$D$8 -> 0.12896516 | K4: =(C4-B4)/ABS(B4) -> 0.088235294 | L4: =(D4-C4)/ABS(C4) -> 0.67567568 | M4: =+IF(ABS(K4)<10%,"Low",IF(ABS(K4)<20%,"Medium",IF(ABS(K4)<30%,"High","Extraordinary"))) -> Low | N4: =+IF(ABS(L4)<10%,"Low",IF(ABS(L4)<20%,"Medium",IF(ABS(L4)<30%,"High","Extraordinary"))) -> Extraordinary | O4: =IF(MAX(H4:J4)>=10%,"Large",IF(MAX(H4:J4)>=5%,"Medium","Small")) -> Large
A5: Agency Fees | B5: 310 | C5: 340 | D5: 385 | E5: =+'IncomeStatement check'!$B5/$B$8 -> 0.04431737 | F5: =+'IncomeStatement check'!$C5/$C$8 -> 0.043506078 | G5: =+'IncomeStatement check'!$D5/$D$8 -> 0.040041602 | H5: =+B5/$B$8 -> 0.04431737 | I5: =+C5/$C$8 -> 0.043506078 | J5: =+D5/$D$8 -> 0.040041602 | K5: =(C5-B5)/ABS(B5) -> 0.096774194 | L5: =(D5-C5)/ABS(C5) -> 0.13235294 | M5: =+IF(ABS(K5)<10%,"Low",IF(ABS(K5)<20%,"Medium",IF(ABS(K5)<30%,"High","Extraordinary"))) -> Low | N5: =+IF(ABS(L5)<10%,"Low",IF(ABS(L5)<20%,"Medium",IF(ABS(L5)<30%,"High","Extraordinary"))) -> Medium | O5: =IF(MAX(H5:J5)>=10%,"Large",IF(MAX(H5:J5)>=5%,"Medium","Small")) -> Small
A6: Benefits Division Revenue | B6: 120 | C6: 280 | D6: 520 | E6: =+'IncomeStatement check'!$B6/$B$8 -> 0.017155111 | F6: =+'IncomeStatement check'!$C6/$C$8 -> 0.035828535 | G6: =+'IncomeStatement check'!$D6/$D$8 -> 0.054082163 | H6: =+B6/$B$8 -> 0.017155111 | I6: =+C6/$C$8 -> 0.035828535 | J6: =+D6/$D$8 -> 0.054082163 | K6: =(C6-B6)/ABS(B6) -> 1.3333333 | L6: =(D6-C6)/ABS(C6) -> 0.85714286 | M6: =+IF(ABS(K6)<10%,"Low",IF(ABS(K6)<20%,"Medium",IF(ABS(K6)<30%,"High","Extraordinary"))) -> Extraordinary | N6: =+IF(ABS(L6)<10%,"Low",IF(ABS(L6)<20%,"Medium",IF(ABS(L6)<30%,"High","Extraordinary"))) -> Extraordinary | O6: =IF(MAX(H6:J6)>=10%,"Large",IF(MAX(H6:J6)>=5%,"Medium","Small")) -> Medium
A7: Other Income | B7: 45 | C7: 35 | D7: 290 | E7: =+'IncomeStatement check'!$B7/$B$8 -> 0.0064331665 | F7: =+'IncomeStatement check'!$C7/$C$8 -> 0.0044785669 | G7: =+'IncomeStatement check'!$D7/$D$8 -> 0.030161206 | H7: =+B7/$B$8 -> 0.0064331665 | I7: =+C7/$C$8 -> 0.0044785669 | J7: =+D7/$D$8 -> 0.030161206 | K7: =(C7-B7)/ABS(B7) -> -0.22222222 | L7: =(D7-C7)/ABS(C7) -> 7.2857143 | M7: =+IF(ABS(K7)<10%,"Low",IF(ABS(K7)<20%,"Medium",IF(ABS(K7)<30%,"High","Extraordinary"))) -> High | N7: =+IF(ABS(L7)<10%,"Low",IF(ABS(L7)<20%,"Medium",IF(ABS(L7)<30%,"High","Extraordinary"))) -> Extraordinary | O7: =IF(MAX(H7:J7)>=10%,"Large",IF(MAX(H7:J7)>=5%,"Medium","Small")) -> Small
A8: Total Revenue | B8: 6995 | C8: 7815 | D8: 9615 | E8: =+'IncomeStatement check'!$B8/$B$8 -> 1 | F8: =+'IncomeStatement check'!$C8/$C$8 -> 1 | G8: =+'IncomeStatement check'!$D8/$D$8 -> 1 | H8: =+B8/$B$8 -> 1 | I8: =+C8/$C$8 -> 1 | J8: =+D8/$D$8 -> 1 | K8: =(C8-B8)/ABS(B8) -> 0.11722659 | L8: =(D8-C8)/ABS(C8) -> 0.2303263 | M8: =+IF(ABS(K8)<10%,"Low",IF(ABS(K8)<20%,"Medium",IF(ABS(K8)<30%,"High","Extraordinary"))) -> Medium | N8: =+IF(ABS(L8)<10%,"Low",IF(ABS(L8)<20%,"Medium",IF(ABS(L8)<30%,"High","Extraordinary"))) -> High | O8: =IF(MAX(H8:J8)>=10%,"Large",IF(MAX(H8:J8)>=5%,"Medium","Small")) -> Large
A9: Producer Compensation | B9: 1960 | C9: 2180 | D9: 2620 | E9: =+'IncomeStatement check'!$B9/$B$23 -> 0.43410853 | F9: =+'IncomeStatement check'!$C9/$C$23 -> 0.43151227 | G9: =+'IncomeStatement check'!$D9/$D$23 -> 0.40995149 | H9: =+B9/$B$8 -> 0.28020014 | I9: =+C9/$C$8 -> 0.27895074 | J9: =+D9/$D$8 -> 0.2724909 | K9: =(C9-B9)/ABS(B9) -> 0.1122449 | L9: =(D9-C9)/ABS(C9) -> 0.20183486 | M9: =+IF(ABS(K9)<10%,"Low",IF(ABS(K9)<20%,"Medium",IF(ABS(K9)<30%,"High","Extraordinary"))) -> Medium | N9: =+IF(ABS(L9)<10%,"Low",IF(ABS(L9)<20%,"Medium",IF(ABS(L9)<30%,"High","Extraordinary"))) -> High | O9: =IF(MAX(H9:J9)>=10%,"Large",IF(MAX(H9:J9)>=5%,"Medium","Small")) -> Large
A10: Account Manager / CSR Salaries | B10: 680 | C10: 740 | D10: 810 | E10: =+'IncomeStatement check'!$B10/$B$23 -> 0.15060908 | F10: =+'IncomeStatement check'!$C10/$C$23 -> 0.14647664 | G10: =+'IncomeStatement check'!$D10/$D$23 -> 0.12674073 | H10: =+B10/$B$8 -> 0.097212294 | I10: =+C10/$C$8 -> 0.094689699 | J10: =+D10/$D$8 -> 0.08424337 | K10: =(C10-B10)/ABS(B10) -> 0.088235294 | L10: =(D10-C10)/ABS(C10) -> 0.094594595 | M10: =+IF(ABS(K10)<10%,"Low",IF(ABS(K10)<20%,"Medium",IF(ABS(K10)<30%,"High","Extraordinary"))) -> Low | N10: =+IF(ABS(L10)<10%,"Low",IF(ABS(L10)<20%,"Medium",IF(ABS(L10)<30%,"High","Extraordinary"))) -> Low | O10: =IF(MAX(H10:J10)>=10%,"Large",IF(MAX(H10:J10)>=5%,"Medium","Small")) -> Medium
A11: Administrative Salaries | B11: 320 | C11: 345 | D11: 370 | E11: =+'IncomeStatement check'!$B11/$B$23 -> 0.070874862 | F11: =+'IncomeStatement check'!$C11/$C$23 -> 0.068289786 | G11: =+'IncomeStatement check'!$D11/$D$23 -> 0.057893913 | H11: =+B11/$B$8 -> 0.045746962 | I11: =+C11/$C$8 -> 0.044145873 | J11: =+D11/$D$8 -> 0.038481539 | K11: =(C11-B11)/ABS(B11) -> 0.078125 | L11: =(D11-C11)/ABS(C11) -> 0.072463768 | M11: =+IF(ABS(K11)<10%,"Low",IF(ABS(K11)<20%,"Medium",IF(ABS(K11)<30%,"High","Extraordinary"))) -> Low | N11: =+IF(ABS(L11)<10%,"Low",IF(ABS(L11)<20%,"Medium",IF(ABS(L11)<30%,"High","Extraordinary"))) -> Low | O11: =IF(MAX(H11:J11)>=10%,"Large",IF(MAX(H11:J11)>=5%,"Medium","Small")) -> Small
A12: Owner Compensation (W-2) | B12: 350 | C12: 390 | D12: 450 | E12: =+'IncomeStatement check'!$B12/$B$23 -> 0.07751938 | F12: =+'IncomeStatement check'!$C12/$C$23 -> 0.07719715 | G12: =+'IncomeStatement check'!$D12/$D$23 -> 0.070411516 | H12: =+B12/$B$8 -> 0.05003574 | I12: =+C12/$C$8 -> 0.049904031 | J12: =+D12/$D$8 -> 0.046801872 | K12: =(C12-B12)/ABS(B12) -> 0.11428571 | L12: =(D12-C12)/ABS(C12) -> 0.15384615 | M12: =+IF(ABS(K12)<10%,"Low",IF(ABS(K12)<20%,"Medium",IF(ABS(K12)<30%,"High","Extraordinary"))) -> Medium | N12: =+IF(ABS(L12)<10%,"Low",IF(ABS(L12)<20%,"Medium",IF(ABS(L12)<30%,"High","Extraordinary"))) -> Medium | O12: =IF(MAX(H12:J12)>=10%,"Large",IF(MAX(H12:J12)>=5%,"Medium","Small")) -> Medium
A13: Payroll Taxes & Benefits | B13: 510 | C13: 580 | D13: 655 | E13: =+'IncomeStatement check'!$B13/$B$23 -> 0.11295681 | F13: =+'IncomeStatement check'!$C13/$C$23 -> 0.11480602 | G13: =+'IncomeStatement check'!$D13/$D$23 -> 0.10248787 | H13: =+B13/$B$8 -> 0.072909221 | I13: =+C13/$C$8 -> 0.074216251 | J13: =+D13/$D$8 -> 0.068122725 | K13: =(C13-B13)/ABS(B13) -> 0.1372549 | L13: =(D13-C13)/ABS(C13) -> 0.12931034 | M13: =+IF(ABS(K13)<10%,"Low",IF(ABS(K13)<20%,"Medium",IF(ABS(K13)<30%,"High","Extraordinary"))) -> Medium | N13: =+IF(ABS(L13)<10%,"Low",IF(ABS(L13)<20%,"Medium",IF(ABS(L13)<30%,"High","Extraordinary"))) -> Medium | O13: =IF(MAX(H13:J13)>=10%,"Large",IF(MAX(H13:J13)>=5%,"Medium","Small")) -> Medium
A14: Rent & Occupancy | B14: 165 | C14: 168 | D14: 285 | E14: =+'IncomeStatement check'!$B14/$B$23 -> 0.03654485 | F14: =+'IncomeStatement check'!$C14/$C$23 -> 0.033254157 | G14: =+'IncomeStatement check'!$D14/$D$23 -> 0.04459396 | H14: =+B14/$B$8 -> 0.023588277 | I14: =+C14/$C$8 -> 0.021497121 | J14: =+D14/$D$8 -> 0.029641186 | K14: =(C14-B14)/ABS(B14) -> 0.018181818 | L14: =(D14-C14)/ABS(C14) -> 0.69642857 | M14: =+IF(ABS(K14)<10%,"Low",IF(ABS(K14)<20%,"Medium",IF(ABS(K14)<30%,"High","Extraordinary"))) -> Low | N14: =+IF(ABS(L14)<10%,"Low",IF(ABS(L14)<20%,"Medium",IF(ABS(L14)<30%,"High","Extraordinary"))) -> Extraordinary | O14: =IF(MAX(H14:J14)>=10%,"Large",IF(MAX(H14:J14)>=5%,"Medium","Small")) -> Small
A15: Technology & AMS Licensing | B15: 95 | C15: 140 | D15: 185 | E15: =+'IncomeStatement check'!$B15/$B$23 -> 0.021040975 | F15: =+'IncomeStatement check'!$C15/$C$23 -> 0.027711797 | G15: =+'IncomeStatement check'!$D15/$D$23 -> 0.028946957 | H15: =+B15/$B$8 -> 0.013581129 | I15: =+C15/$C$8 -> 0.017914267 | J15: =+D15/$D$8 -> 0.01924077 | K15: =(C15-B15)/ABS(B15) -> 0.47368421 | L15: =(D15-C15)/ABS(C15) -> 0.32142857 | M15: =+IF(ABS(K15)<10%,"Low",IF(ABS(K15)<20%,"Medium",IF(ABS(K15)<30%,"High","Extraordinary"))) -> Extraordinary | N15: =+IF(ABS(L15)<10%,"Low",IF(ABS(L15)<20%,"Medium",IF(ABS(L15)<30%,"High","Extraordinary"))) -> Extraordinary | O15: =IF(MAX(H15:J15)>=10%,"Large",IF(MAX(H15:J15)>=5%,"Medium","Small")) -> Small
A16: E&O Insurance (Agency) | B16: 85 | C16: 92 | D16: 98 | E16: =+'IncomeStatement check'!$B16/$B$23 -> 0.018826135 | F16: =+'IncomeStatement check'!$C16/$C$23 -> 0.01821061 | G16: =+'IncomeStatement check'!$D16/$D$23 -> 0.015334064 | H16: =+B16/$B$8 -> 0.012151537 | I16: =+C16/$C$8 -> 0.011772233 | J16: =+D16/$D$8 -> 0.010192408 | K16: =(C16-B16)/ABS(B16) -> 0.082352941 | L16: =(D16-C16)/ABS(C16) -> 0.065217391 | M16: =+IF(ABS(K16)<10%,"Low",IF(ABS(K16)<20%,"Medium",IF(ABS(K16)<30%,"High","Extraordinary"))) -> Low | N16: =+IF(ABS(L16)<10%,"Low",IF(ABS(L16)<20%,"Medium",IF(ABS(L16)<30%,"High","Extraordinary"))) -> Low | O16: =IF(MAX(H16:J16)>=10%,"Large",IF(MAX(H16:J16)>=5%,"Medium","Small")) -> Small
A17: Marketing & Business Development | B17: 110 | C17: 135 | D17: 280 | E17: =+'IncomeStatement check'!$B17/$B$23 -> 0.024363234 | F17: =+'IncomeStatement check'!$C17/$C$23 -> 0.02672209 | G17: =+'IncomeStatement check'!$D17/$D$23 -> 0.04381161 | H17: =+B17/$B$8 -> 0.015725518 | I17: =+C17/$C$8 -> 0.017274472 | J17: =+D17/$D$8 -> 0.029121165 | K17: =(C17-B17)/ABS(B17) -> 0.22727273 | L17: =(D17-C17)/ABS(C17) -> 1.0740741 | M17: =+IF(ABS(K17)<10%,"Low",IF(ABS(K17)<20%,"Medium",IF(ABS(K17)<30%,"High","Extraordinary"))) -> High | N17: =+IF(ABS(L17)<10%,"Low",IF(ABS(L17)<20%,"Medium",IF(ABS(L17)<30%,"High","Extraordinary"))) -> Extraordinary | O17: =IF(MAX(H17:J17)>=10%,"Large",IF(MAX(H17:J17)>=5%,"Medium","Small")) -> Small
A18: Travel & Entertainment | B18: 75 | C18: 88 | D18: 195 | E18: =+'IncomeStatement check'!$B18/$B$23 -> 0.016611296 | F18: =+'IncomeStatement check'!$C18/$C$23 -> 0.017418844 | G18: =+'IncomeStatement check'!$D18/$D$23 -> 0.030511657 | H18: =+B18/$B$8 -> 0.010721944 | I18: =+C18/$C$8 -> 0.011260397 | J18: =+D18/$D$8 -> 0.020280811 | K18: =(C18-B18)/ABS(B18) -> 0.17333333 | L18: =(D18-C18)/ABS(C18) -> 1.2159091 | M18: =+IF(ABS(K18)<10%,"Low",IF(ABS(K18)<20%,"Medium",IF(ABS(K18)<30%,"High","Extraordinary"))) -> Medium | N18: =+IF(ABS(L18)<10%,"Low",IF(ABS(L18)<20%,"Medium",IF(ABS(L18)<30%,"High","Extraordinary"))) -> Extraordinary | O18: =IF(MAX(H18:J18)>=10%,"Large",IF(MAX(H18:J18)>=5%,"Medium","Small")) -> Small
A19: Professional Fees (Legal/Accounting) | B19: 60 | C19: 72 | D19: 165 | E19: =+'IncomeStatement check'!$B19/$B$23 -> 0.013289037 | F19: =+'IncomeStatement check'!$C19/$C$23 -> 0.014251781 | G19: =+'IncomeStatement check'!$D19/$D$23 -> 0.025817556 | H19: =+B19/$B$8 -> 0.0085775554 | I19: =+C19/$C$8 -> 0.0092130518 | J19: =+D19/$D$8 -> 0.017160686 | K19: =(C19-B19)/ABS(B19) -> 0.2 | L19: =(D19-C19)/ABS(C19) -> 1.2916667 | M19: =+IF(ABS(K19)<10%,"Low",IF(ABS(K19)<20%,"Medium",IF(ABS(K19)<30%,"High","Extraordinary"))) -> High | N19: =+IF(ABS(L19)<10%,"Low",IF(ABS(L19)<20%,"Medium",IF(ABS(L19)<30%,"High","Extraordinary"))) -> Extraordinary | O19: =IF(MAX(H19:J19)>=10%,"Large",IF(MAX(H19:J19)>=5%,"Medium","Small")) -> Small
A20: Carrier Licensing & Continuing Ed. | B20: 32 | C20: 35 | D20: 38 | E20: =+'IncomeStatement check'!$B20/$B$23 -> 0.0070874862 | F20: =+'IncomeStatement check'!$C20/$C$23 -> 0.0069279493 | G20: =+'IncomeStatement check'!$D20/$D$23 -> 0.0059458614 | H20: =+B20/$B$8 -> 0.0045746962 | I20: =+C20/$C$8 -> 0.0044785669 | J20: =+D20/$D$8 -> 0.0039521581 | K20: =(C20-B20)/ABS(B20) -> 0.09375 | L20: =(D20-C20)/ABS(C20) -> 0.085714286 | M20: =+IF(ABS(K20)<10%,"Low",IF(ABS(K20)<20%,"Medium",IF(ABS(K20)<30%,"High","Extraordinary"))) -> Low | N20: =+IF(ABS(L20)<10%,"Low",IF(ABS(L20)<20%,"Medium",IF(ABS(L20)<30%,"High","Extraordinary"))) -> Low | O20: =IF(MAX(H20:J20)>=10%,"Large",IF(MAX(H20:J20)>=5%,"Medium","Small")) -> Small
... A23: Total Operating Expenses | B23: 4515 | C23: 5052 | D23: 6391 | E23: =+'IncomeStatement check'!$B23/$B$23 -> 1 | F23: =+'IncomeStatement check'!$C23/$C$23 -> 1 | G23: =+'IncomeStatement check'!$D23/$D$23 -> 1 | H23: =+B23/$B$8 -> 0.64546104 | I23: =+C23/$C$8 -> 0.64644914 | J23: =+D23/$D$8 -> 0.66469059 | K23: =(C23-B23)/ABS(B23) -> 0.11893688 | L23: =(D23-C23)/ABS(C23) -> 0.26504355 | M23: =+IF(ABS(K23)<10%,"Low",IF(ABS(K23)<20%,"Medium",IF(ABS(K23)<30%,"High","Extraordinary"))) -> Medium | N23: =+IF(ABS(L23)<10%,"Low",IF(ABS(L23)<20%,"Medium",IF(ABS(L23)<30%,"High","Extraordinary"))) -> High | O23: =IF(MAX(H23:J23)>=10%,"Large",IF(MAX(H23:J23)>=5%,"Medium","Small")) -> Large
A24: Operating Income (EBIT) | B24: 2480 | C24: 2763 | D24: 3224 | H24: =+B24/$B$8 -> 0.35453896 | I24: =+C24/$C$8 -> 0.35355086 | J24: =+D24/$D$8 -> 0.33530941 | K24: =(C24-B24)/ABS(B24) -> 0.1141129 | L24: =(D24-C24)/ABS(C24) -> 0.16684763 | M24: =+IF(ABS(K24)<10%,"Low",IF(ABS(K24)<20%,"Medium",IF(ABS(K24)<30%,"High","Extraordinary"))) -> Medium | N24: =+IF(ABS(L24)<10%,"Low",IF(ABS(L24)<20%,"Medium",IF(ABS(L24)<30%,"High","Extraordinary"))) -> Medium | O24: =IF(MAX(H24:J24)>=10%,"Large",IF(MAX(H24:J24)>=5%,"Medium","Small")) -> Large
A25: Interest Expense | B25: 25 | C25: 22 | D25: 68 | H25: =+B25/$B$8 -> 0.0035739814 | I25: =+C25/$C$8 -> 0.0028150992 | J25: =+D25/$D$8 -> 0.0070722829 | K25: =(C25-B25)/ABS(B25) -> -0.12 | L25: =(D25-C25)/ABS(C25) -> 2.0909091 | M25: =+IF(ABS(K25)<10%,"Low",IF(ABS(K25)<20%,"Medium",IF(ABS(K25)<30%,"High","Extraordinary"))) -> Medium | N25: =+IF(ABS(L25)<10%,"Low",IF(ABS(L25)<20%,"Medium",IF(ABS(L25)<30%,"High","Extraordinary"))) -> Extraordinary | O25: =IF(MAX(H25:J25)>=10%,"Large",IF(MAX(H25:J25)>=5%,"Medium","Small")) -> Small
A26: Other Non-Operating Income / (Expense) | B26: 8 | C26: -5 | D26: 15 | H26: =+B26/$B$8 -> 0.0011436741 | I26: =+C26/$C$8 -> -0.00063979527 | J26: =+D26/$D$8 -> 0.0015600624 | K26: =(C26-B26)/ABS(B26) -> -1.625 | L26: =(D26-C26)/ABS(C26) -> 4 | M26: =+IF(ABS(K26)<10%,"Low",IF(ABS(K26)<20%,"Medium",IF(ABS(K26)<30%,"High","Extraordinary"))) -> Extraordinary | N26: =+IF(ABS(L26)<10%,"Low",IF(ABS(L26)<20%,"Medium",IF(ABS(L26)<30%,"High","Extraordinary"))) -> Extraordinary | O26: =IF(MAX(H26:J26)>=10%,"Large",IF(MAX(H26:J26)>=5%,"Medium","Small")) -> Small
A27: Net Income Before Tax | B27: 2463 | C27: 2736 | D27: 3171 | H27: =+B27/$B$8 -> 0.35210865 | I27: =+C27/$C$8 -> 0.35009597 | J27: =+D27/$D$8 -> 0.32979719 | K27: =(C27-B27)/ABS(B27) -> 0.11084044 | L27: =(D27-C27)/ABS(C27) -> 0.15899123 | M27: =+IF(ABS(K27)<10%,"Low",IF(ABS(K27)<20%,"Medium",IF(ABS(K27)<30%,"High","Extraordinary"))) -> Medium | N27: =+IF(ABS(L27)<10%,"Low",IF(ABS(L27)<20%,"Medium",IF(ABS(L27)<30%,"High","Extraordinary"))) -> Medium | O27: =IF(MAX(H27:J27)>=10%,"Large",IF(MAX(H27:J27)>=5%,"Medium","Small")) -> Large
A28: Income Tax Provision | B28: 0 | C28: 0 | D28: 0 | H28: =+B28/$B$8 -> 0 | I28: =+C28/$C$8 -> 0 | J28: =+D28/$D$8 -> 0 | K28: 0 | L28: 0 | M28: =+IF(ABS(K28)<10%,"Low",IF(ABS(K28)<20%,"Medium",IF(ABS(K28)<30%,"High","Extraordinary"))) -> Low | N28: =+IF(ABS(L28)<10%,"Low",IF(ABS(L28)<20%,"Medium",IF(ABS(L28)<30%,"High","Extraordinary"))) -> Low | O28: =IF(MAX(H28:J28)>=10%,"Large",IF(MAX(H28:J28)>=5%,"Medium","Small")) -> Small
A29: Net Income | B29: 2463 | C29: 2736 | D29: 3171 | H29: =+B29/$B$8 -> 0.35210865 | I29: =+C29/$C$8 -> 0.35009597 | J29: =+D29/$D$8 -> 0.32979719 | K29: =(C29-B29)/ABS(B29) -> 0.11084044 | L29: =(D29-C29)/ABS(C29) -> 0.15899123 | M29: =+IF(ABS(K29)<10%,"Low",IF(ABS(K29)<20%,"Medium",IF(ABS(K29)<30%,"High","Extraordinary"))) -> Medium | N29: =+IF(ABS(L29)<10%,"Low",IF(ABS(L29)<20%,"Medium",IF(ABS(L29)<30%,"High","Extraordinary"))) -> Medium | O29: =IF(MAX(H29:J29)>=10%,"Large",IF(MAX(H29:J29)>=5%,"Medium","Small")) -> Large

Sheet Balance Sheet
A1: Exhibit 2: Balance Sheets (FY 2023–2025) (All figures in USD thousands)
A2: Column1 | B2: FY 2023 | C2: FY 2024 | D2: FY 2025
A3: ASSETS
A4: Cash & Cash Equivalents | B4: 520 | C4: 680 | D4: 490
A5: Commissions Receivable | B5: 840 | C5: 960 | D5: 1380
A6: Contingent Commission Receivable | B6: 0 | C6: 0 | D6: 410
A7: Prepaid Expenses | B7: 45 | C7: 52 | D7: 68
A8: Other Current Assets | B8: 20 | C8: 15 | D8: 95
A9: Total Current Assets | B9: 1425 | C9: 1707 | D9: 2443
A11: Furniture & Equipment (net) | B11: 120 | C11: 105 | D11: 92
A12: Leasehold Improvements (net) | B12: 35 | C12: 28 | D12: 185
A13: Intangible Assets — Book of Business | B13: 0 | C13: 0 | D13: 840
A14: Goodwill | B14: 0 | C14: 0 | D14: 320
A15: Other Long-Term Assets | B15: 30 | C15: 30 | D15: 30
A16: Total Assets | B16: 1610 | C16: 1870 | D16: 3910
A18: LIABILITIES
A19: Accounts Payable | B19: 180 | C19: 210 | D19: 340
A20: Premiums Payable to Carriers | B20: 1240 | C20: 1380 | D20: 1680
A21: Accrued Compensation | B21: 280 | C21: 310 | D21: 395
A22: Current Portion of Notes Payable | B22: 0 | C22: 0 | D22: 180
A23: Total Current Liabilities | B23: 1700 | C23: 1900 | D23: 2595
A25: Notes Payable — Book Purchase | B25: 0 | C25: 0 | D25: 720
A26: Line of Credit | B26: 0 | C26: 0 | D26: 150
A27: Total Liabilities | B27: 1700 | C27: 1900 | D27: 3465
A29: EQUITY
A30: Member’s Capital | B30: 50 | C30: 50 | D30: 50
A31: Retained Earnings | B31: -140 | C31: -80 | D31: 395
A32: Total Equity | B32: -90 | C32: -30 | D32: 445
A34: Total Liabilities & Equity | B34: 1610 | C34: 1870 | D34: 3910

Sheet P&C comissionIncome
A1: P&C Commission Income by Line of Business
A2: Line of Business | B2: Written Premium | C2: Avg. Commission % | D2: Commission Revenue | E2: % of P&C Revenue
A3: Commercial Property | B3: 18200 | C3: 0.125 | D3: 2275 | E3: 0.317
A4: General Liability | B4: 14600 | C4: 0.13 | D4: 1898 | E4: 0.264
A5: Professional Liability (E&O) | B5: 6800 | C5: 0.145 | D5: 986 | E5: 0.137
A6: Workers’ Compensation | B6: 5400 | C6: 0.1 | D6: 540 | E6: 0.075
A7: Commercial Auto | B7: 4200 | C7: 0.11 | D7: 462 | E7: 0.064
A8: Inland Marine / Specialty | B8: 3800 | C8: 0.15 | D8: 570 | E8: 0.079
A9: Umbrella / Excess | B9: 3200 | C9: 0.14 | D9: 449 | E9: 0.063
A11: Total P&C | B11: 56200 | C11: 12.8% (blended) | D11: 7180 | E11: 1

Sheet Contingent Comission Detailes
A1: Contingent Commission Detail
A2: Carrier | B2: FY 2023 | C2: FY 2024 | D2: FY 2025 | E2: Notes
A3: Everest National | B3: 240 | C3: 260 | D3: 310 | E3: Profit-sharing; stable
A4: SouthCoast Mutual | B4: 180 | C4: 195 | D4: 210 | E4: Volume-based; stable
A5: Atlantic Specialty Group | B5: 140 | C5: 155 | D5: 170 | E5: Growth bonus; stable
A6: Patriot Underwriters | B6: 120 | C6: 130 | D6: 145 | E6: Profit-sharing; stable
A7: New — Coastal Surplus Lines | B7: 0 | C7: 0 | D7: 405 | E7: First year; one-time signing bonus component
A9: Total Contingent Commissions | B9: 680 | C9: 740 | D9: 1240

Sheet Top10Accounts
A1: Top 10 Accounts by FY 2025 Revenue
A2: Account | B2: Revenue | C2: % of Total | D2: Primary Line
A3: Marchetti Development Group, LLC | B3: 620 | C3: 0.064 | D3: Property / GL / WC
A4: SunBelt Hospitality Partners | B4: 540 | C4: 0.056 | D4: Property / GL / Liquor
A5: Tri-County Medical Associates | B5: 480 | C5: 0.05 | D5: Professional Liability
A6: Gulf Atlantic Marine Services | B6: 420 | C6: 0.044 | D6: Marine / GL / WC
A7: Broward Commercial Realty Trust | B7: 380 | C7: 0.04 | D7: Property / Umbrella
A8: Southeast Contractors Alliance | B8: 340 | C8: 0.035 | D8: GL / WC / Auto
A9: Coastal Living Communities | B9: 310 | C9: 0.032 | D9: Property / GL
A10: Premier Dining Concepts | B10: 280 | C10: 0.029 | D10: Property / GL / Liquor
A11: Florida Physicians Network | B11: 240 | C11: 0.025 | D11: Professional Liability
A12: Port Everglades Logistics | B12: 220 | C12: 0.023 | D12: Marine / Cargo / GL
A14: Top 10 Subtotal | B14: 3830 | C14: 0.398
A15: All Other Accounts (~380 policies) | B15: 5785 | C15: 0.602

Sheet BankActivity
A1: Exhibit 3: Summarized Bank Activity — FY 2025 (Primary Operating Account) (All figures in USD thousands)
A2: Month | B2: Deposits | C2: Disbursements | D2: Ending Balance
A3: January | B3: 780 | C3: 740 | D3: 530
A4: February | B4: 720 | C4: 690 | D4: 560
A5: March | B5: 840 | C5: 810 | D5: 590
A6: April | B6: 950 | C6: 880 | D6: 660
A7: May | B7: 810 | C7: 820 | D7: 650
A8: June | B8: 1080 | C8: 960 | D8: 770
A9: July | B9: 860 | C9: 840 | D9: 790
A10: August | B10: 790 | C10: 810 | D10: 770
A11: September | B11: 920 | C11: 870 | D11: 820
A12: October | B12: 1150 | C12: 1080 | D12: 890
A13: November | B13: 880 | C13: 920 | D13: 850
A14: December | B14: 740 | C14: 1100 | D14: 490
A16: Full Year Total | B16: 10520 | C16: 10520
A19: Note: This reflects only the primary operating account. The agency maintains a separate premium trust account for fiduciary funds as required by state regulation. Premium trust activity is not reflected above.

Sheet ProducerEcon&Compen
A1: Exhibit 5: Producer Economics & Compensation Summary (FY 2025)
A2: Producer | B2: Book Revenue | C2: % of Agency | D2: Comp Structure | E2: Total Comp | F2: Comp as % of Book
A3: Tony Marchetti (owner) | B3: 2840 | C3: 0.295 | D3: W-2 + distributions | E3: $450 (W-2) | F3: 15.8% (W-2 only)
A4: Jennifer Oakes | B4: 1680 | C4: 0.175 | D4: Base + 35% commission | E4: 628 | F4: 0.374
A5: Carlos Medina | B5: 1240 | C5: 0.129 | D5: Base + 30% commission | E5: 412 | F5: 0.332
A6: David Park | B6: 920 | C6: 0.096 | D6: Base + 30% commission | E6: 316 | F6: 0.343
A7: Sarah Whitfield | B7: 680 | C7: 0.071 | D7: Base + 28% commission | E7: 230 | F7: 0.338
A8: Ryan Torres | B8: 440 | C8: 0.046 | D8: Base + 25% commission | E8: 160 | F8: 0.364
A9: Michelle Kaplan (benefits) | B9: 520 | C9: 0.054 | D9: Base + 20% on new | E9: 145 | F9: 0.279
A10: House accounts (no producer) | B10: 1295 | C10: 0.135 | D10: Serviced by CSRs | E10: — | F10: —
A12: Total | B12: 9615 | C12: 1 | E12: $2,341*
A14: * Total producer comp of $2,341K shown here differs from the $2,620K “Producer Compensation” line on the P&L. Management states the difference ($279K) relates to a signing bonus for a new producer hired in Q4 2025 and a retention bonus paid to Jennifer Oakes.

Sheet OwnerCompen
A1: Exhibit 6: Owner Compensation & Related-Party Summary
A2: Item | B2: FY 2023 | C2: FY 2024 | D2: FY 2025
A3: Owner W-2 Compensation | B3: 350 | C3: 390 | D3: 450
A4: S-Corp Distributions | B4: 1800 | C4: 2050 | D4: 2280
A5: Personal Vehicle (Porsche Cayenne) | B5: 0 | C5: 24 | D5: 24
A6: Country Club (Boca Raton Resort) | B6: 0 | C6: 32 | D6: 32
A7: Suite / Hospitality (Miami Heat) | B7: 0 | C7: 0 | D7: 45
A8: Family Health Insurance | B8: 22 | C8: 24 | D8: 28
A9: Life / Disability (owner only) | B9: 15 | C9: 15 | D9: 15
A11: Marchetti Development Group, LLC — Insurance | B11: $620 premiums | C11: $580 premiums | D11: $620 premiums
A12: Marchetti Development Group, LLC — Office Lease | B12: 0 | C12: 0 | D12: $120 (July start)
A14: Note: In July 2025, CRA relocated to a Class A office space in a building owned by Marchetti Development Group, LLC (100% owned by Tony Marchetti and his wife). The prior office lease with an unrelated landlord was $168K/year. The new lease is $240K/year (annualized), of which only $120K is reflected in FY 2025 (6 months). Tony states the new space is larger and includes a client conference center.

Sheet Notes
A1: Book of Business Acquisition: In January 2025, CRA acquired a small book of commercial property business from a retiring sole-proprietor agent for $1.16M ($840K allocated to book of business intangible, $320K to goodwill). Financed with a $900K seller note (5-year, 6% interest) and $260K cash. The acquired book generated approximately $480K in commission revenue in FY 2025. Retention on acquired accounts is tracking at approximately 72% through December 2025.
A3: Contingent Commission Spike: FY 2025 contingent commissions increased 68% YoY. Management states that $405K of the increase relates to a new carrier relationship (Coastal Surplus Lines) that included a one-time $250K signing/onboarding bonus in the first-year contingent payment.
A5: Benefits Division Growth: Benefits revenue grew from $120K (FY 2023) to $520K (FY 2025). Tony states this division is “the future of the agency” but it currently operates at approximately breakeven after allocating Michelle Kaplan’s compensation and dedicated technology costs.
A7: Technology Costs: FY 2025 includes $48K in one-time AMS migration consulting fees (Hawksoft to Applied Epic conversion completed in Q1 2025) and $22K in data cleanup costs
A9: Marketing Spend Spike: FY 2025 marketing includes $95K for a full agency rebrand (new logo, website, collateral) and $40K for Tony’s personal speaking engagements at three industry conferences, including travel for his wife
A11: Professional Fees: FY 2025 includes $72K in legal fees related to an E&O claim filed by a former client alleging failure to procure adequate coverage. The claim is ongoing; agency E&O carrier is defending. No reserve has been recorded.
A13: Rent & Occupancy: The jump from $168K (FY 2024) to $285K (FY 2025) reflects six months at the old location plus six months at the new Marchetti-owned building. The annualized run-rate at the new location is $240K.
A15: Retention Rates: Overall client retention rate was 89% in FY 2025, down from 92% in FY 2024 and 93% in FY 2023. Tony attributes the decline to “market hardening” in commercial property. The agency does not track retention by producer.
A17: Other Income (FY 2025): Includes a $225K referral fee received from a personal lines agency to which CRA referred its entire personal lines book in late 2024. Tony states this was a one-time strategic decision to exit personal lines entirely.

Sheet Sheet9
